midi_viewer_live.py
midi_viewer-0.0.1.dist-info/METADATA
midi_viewer-0.0.1.dist-info/WHEEL
midi_viewer-0.0.1.dist-info/entry_points.txt
midi_viewer-0.0.1.dist-info/top_level.txt
midi_viewer-0.0.1.dist-info/RECORD
