Metadata-Version: 2.1
Name: midi-viewer
Version: 0.0.1
Summary: Basic midi keyboard display tool for use as a teaching aid.
Home-page: UNKNOWN
Author: Marco Bolt
Author-email: UNKNOWN
License: UNKNOWN
Platform: UNKNOWN
Classifier: Programming Language :: Python :: 3.8
Requires-Dist: PyQt5
Requires-Dist: pygame (==2.0.0.dev18)
